phalp/__init__.py
phalp/deep_sort_/__init__.py
phalp/deep_sort_/detection.py
phalp/deep_sort_/linear_assignment.py
phalp/deep_sort_/nn_matching.py
phalp/deep_sort_/track.py
phalp/deep_sort_/tracker.py
phalp/models/__init__.py
phalp/models/hmar.py
phalp/models/joint_mapper.py
phalp/models/pose_transformer.py
phalp/models/backbones/__init__.py
phalp/models/backbones/resnet.py
phalp/models/heads/__init__.py
phalp/models/heads/apperence_head.py
phalp/models/heads/encoding_head.py
phalp/models/heads/mesh.py
phalp/models/heads/smpl_head.py
phalp/models/heads/smpl_head_prediction.py
phalp/models/smplx/__init__.py
phalp/models/smplx/body_models.py
phalp/models/smplx/joint_names.py
phalp/models/smplx/lbs.py
phalp/models/smplx/utils.py
phalp/models/smplx/vertex_ids.py
phalp/models/smplx/vertex_joint_selector.py
phalp/models/transformers/__init__.py
phalp/models/transformers/relational_model.py
phalp/models/transformers/relational_model_utils.py
phalp/trackers/PHALP.py
phalp/trackers/__init__.py
phalp/utils/__init__.py
phalp/utils/pylogger.py
phalp/utils/utils.py
phalp/utils/utils_dataset.py
phalp/utils/utils_detectron2.py
phalp/utils/utils_measure.py
phalp/utils/utils_scenedetect.py
phalp/visualize/__init__.py
phalp/visualize/py_renderer.py
phalp/visualize/visualizer.py
phalp-0.1.3.dist-info/LICENSE
phalp-0.1.3.dist-info/METADATA
phalp-0.1.3.dist-info/WHEEL
phalp-0.1.3.dist-info/top_level.txt
phalp-0.1.3.dist-info/RECORD
