Metadata-Version: 2.1
Name: phalp
Version: 0.1.3
Summary: PHALP: A Python package for People Tracking in 3D
Home-page: https://github.com/brjathu/PHALP
Author: Jathushan Rajasegaran
Author-email: jathushan@berkeley.edu
License: MIT License
Requires-Python: >=3.7
License-File: LICENSE
Requires-Dist: hydra-core
